oteri/__init__.py
oteri/digital_image.py
oteri/vision.py
OpenDIP_Python-0.0.1.dist-info/LICENSE
OpenDIP_Python-0.0.1.dist-info/METADATA
OpenDIP_Python-0.0.1.dist-info/WHEEL
OpenDIP_Python-0.0.1.dist-info/top_level.txt
OpenDIP_Python-0.0.1.dist-info/RECORD
