Metadata-Version: 2.1
Name: OpenDIP-Python
Version: 0.0.1
Summary: Digital Image Processing
Author: Akaawase ( Bernard Akaawase)
Author-email: <my.opendip@gmail.com>
License: UNKNOWN
Keywords: python,image
Platform: UNKNOWN
Classifier: Development Status :: 1 - Planning
Classifier: Intended Audience :: Developers
Classifier: Programming Language :: Python :: 3
Classifier: Operating System :: Unix
Classifier: Operating System :: MacOS :: MacOS X
Classifier: Operating System :: Microsoft :: Windows
License-File: LICENSE
Requires-Dist: opencv-python
Requires-Dist: numpy
Requires-Dist: matplotlib
Requires-Dist: scipy
